.gitignore
.travis.yml
CHANGES.txt
MANIFEST.in
README.rst
bootstrap.py
buildout.cfg
setup.py
wsgi_chronometer/__init__.py
wsgi_chronometer.egg-info/PKG-INFO
wsgi_chronometer.egg-info/SOURCES.txt
wsgi_chronometer.egg-info/dependency_links.txt
wsgi_chronometer.egg-info/entry_points.txt
wsgi_chronometer.egg-info/not-zip-safe
wsgi_chronometer.egg-info/requires.txt
wsgi_chronometer.egg-info/top_level.txt