Metadata-Version: 1.0
Name: wsgi-chronometer
Version: 0.1
Summary: Just a wsgi filter for mesure time execution
Home-page: https://github.com/cyplp/wsgi_chronometer
Author: Cyprien Le Pannérer
Author-email: cyplp@free.fr
License: MIT
Keywords: wsgi time filter
Platform: UNKNOWN
